libpysal/.gitignore
libpysal/__init__.py
libpysal/common.py
libpysal/cg/__init__.py
libpysal/cg/alpha_shapes.py
libpysal/cg/kdtree.py
libpysal/cg/locators.py
libpysal/cg/polygonQuadTreeStructure.py
libpysal/cg/rtree.py
libpysal/cg/segmentLocator.py
libpysal/cg/shapely_ext.py
libpysal/cg/shapes.py
libpysal/cg/sphere.py
libpysal/cg/standalone.py
libpysal/cg/voronoi.py
libpysal/cg/ops/__init__.py
libpysal/cg/ops/_accessors.py
libpysal/cg/ops/_shapely.py
libpysal/cg/ops/atomic.py
libpysal/cg/ops/tabular.py
libpysal/cg/ops/tests/__init__.py
libpysal/cg/ops/tests/test_accessors.py
libpysal/cg/ops/tests/test_shapely.py
libpysal/cg/ops/tests/test_tabular.py
libpysal/cg/tests/__init__.py
libpysal/cg/tests/fast_point_in_polygon_algorithm.ipynb
libpysal/cg/tests/test_ashapes.py
libpysal/cg/tests/test_geoJSON.py
libpysal/cg/tests/test_locators.py
libpysal/cg/tests/test_polygonQuadTreeStructure.py
libpysal/cg/tests/test_rtree.py
libpysal/cg/tests/test_segmentLocator.py
libpysal/cg/tests/test_shapes.py
libpysal/cg/tests/test_sphere.py
libpysal/cg/tests/test_standalone.py
libpysal/cg/tests/test_voronoi.py
libpysal/cg/tests/data/alpha_05.gpkg
libpysal/cg/tests/data/alpha_auto.gpkg
libpysal/cg/tests/data/alpha_fifth.gpkg
libpysal/cg/tests/data/alpha_fourth.gpkg
libpysal/cg/tests/data/alpha_tenth.gpkg
libpysal/cg/tests/data/eberly_bounding_circles.gpkg
libpysal/cg/tests/data/pecos_points.txt
libpysal/cg/tests/data/san_saba_points.txt
libpysal/cg/tests/data/study_region_huangshan_point.txt
libpysal/cg/tests/data/texas_points.txt
libpysal/cg/tests/img/cell_boundary_category_rule.png
libpysal/cg/tests/img/extract_connecting_boders_between_points.png
libpysal/cg/tests/img/quadtree_example.png
libpysal/cg/tests/img/segment_sequence_search_rule.png
libpysal/cg/tests/img/situation_segment_intersect_with_two_split_line.png
libpysal/examples/__init__.py
libpysal/examples/base.py
libpysal/examples/builtin.py
libpysal/examples/remotes.py
libpysal/examples/10740/10740.dbf
libpysal-4.12.1.dist-info/LICENSE.txt
libpysal-4.12.1.dist-info/METADATA
libpysal-4.12.1.dist-info/WHEEL
libpysal-4.12.1.dist-info/top_level.txt
libpysal-4.12.1.dist-info/RECORD
