Metadata-Version: 2.1
Name: libpysal
Version: 4.12.1
Summary: Core components of PySAL - A library of spatial analysis functions
Author-email: Serge Rey <sjsrey@gmail.com>, Levi Wolf <levi.john.wolf@gmail.com>
Maintainer: PySAL Developers
License: BSD 3-Clause
Project-URL: Home, https://github.com/pysal/libpysal/
Project-URL: Repository, https://github.com/pysal/libpysal
Keywords: spatial statistics,spatial graphs
Classifier: Programming Language :: Python :: 3
Classifier: License :: OSI Approved :: BSD License
Classifier: Operating System :: OS Independent
Classifier: Intended Audience :: Science/Research
Classifier: Topic :: Scientific/Engineering :: GIS
Requires-Python: >=3.10
License-File: LICENSE.txt
Requires-Dist: beautifulsoup4>=4.10
Requires-Dist: geopandas>=0.10.0
Requires-Dist: numpy>=1.22
Requires-Dist: packaging>=22
Requires-Dist: pandas>=1.4
Requires-Dist: platformdirs>=2.0.2
Requires-Dist: requests>=2.27
Requires-Dist: scipy>=1.8
Requires-Dist: shapely>=2.0.1
Requires-Dist: scikit-learn>=1.1
Provides-Extra: plus
Requires-Dist: joblib>=1.2; extra == "plus"
Requires-Dist: networkx>=2.7; extra == "plus"
Requires-Dist: numba>=0.55; extra == "plus"
Requires-Dist: pyarrow>=7.0; extra == "plus"
Requires-Dist: sqlalchemy>=2.0; extra == "plus"
Requires-Dist: xarray>=2022.3; extra == "plus"
Requires-Dist: zstd; extra == "plus"
Provides-Extra: dev
Requires-Dist: pre-commit; extra == "dev"
Requires-Dist: ruff; extra == "dev"
Requires-Dist: watermark; extra == "dev"
Provides-Extra: docs
Requires-Dist: myst-parser; extra == "docs"
Requires-Dist: nbsphinx; extra == "docs"
Requires-Dist: numpydoc; extra == "docs"
Requires-Dist: pandoc; extra == "docs"
Requires-Dist: sphinx; extra == "docs"
Requires-Dist: sphinxcontrib-bibtex; extra == "docs"
Requires-Dist: sphinx_bootstrap_theme; extra == "docs"
Provides-Extra: tests
Requires-Dist: codecov; extra == "tests"
Requires-Dist: geodatasets>=2023.3.0; extra == "tests"
Requires-Dist: matplotlib>=3.6; extra == "tests"
Requires-Dist: pytest; extra == "tests"
Requires-Dist: pytest-mpl; extra == "tests"
Requires-Dist: pytest-cov; extra == "tests"
Requires-Dist: pytest-xdist; extra == "tests"
